{
    "meta": {
        "goal_name": "HEARTS",
        "publisher": "World Health Organisation",
        "publication_date": ""
    },
    "body": {
        "weight_control": [{
                "category": "need weight loss",
                "definition": "consider weight loss as soon as possible",
                "conditions": [{
                        "bmi": ["BMI-OBESE", "BMI-OVERWEIGHT"]
                    },
                    {
                        "whr": ["WHR-HIGH"]
                    },
                    {
                        "wst": ["WST-HIGH"]
                    },
                    {
                        "body_fat": ["BFT-OBESE"]
                    },
                    {
                        "bmi": ["BMI-OBESE", "BMI-OVERWEIGHT", "BMI-NORMAL"],
                        "whr": ["WHR-HIGH"],
                        "wst": ["WST-HIGH"],
                        "body_fat": ["BFT-OBESE", "BFT-OVERWEIGHT"]
                    }
                ],
                "code": "WC-1"
            },
            {
                "category": "Need to weight gain",
                "definition": "BMI or Body Fat underweight",
                "conditions": [{
                        "bmi": ["BMI-UNDERWEIGHT"]
                    },
                    {
                        "body_fat": ["BFT-UNDERWEIGHT"]
                    }
                ],
                "code": "WC-2"
            }
        ],
        "smoking_control": [{
                "category": "Encouragement to stay quitting",
                "definition": "Recently quit smoking",
                "conditions": [{
                    "smoking": ["SM-RECENTLY-QUIT"]
                }],
                "code": "SC-1"
            },
            {
                "category": "Current smoker",
                "definition": "Current smoker, set goal for cessation",
                "conditions": [{
                    "smoking": ["SM-CURRENT"]
                }],
                "code": "SC-2"
            }
        ],
        "alcohol_control": [{
            "category": "Reduce alcohol consumption",
            "definition": "Quit or reduce consumption",
            "conditions": [{
                "alcohol": ["ALC-AT-RISK"]
            }],
            "code": "AC-1"
        }],
        "medical_control": [{
                "category": "Moderate CVD risk",
                "definition": "Moderate CVD risk",
                "conditions": [{
                    "cvd": ["CVD-MODERATE-RISK"]
                }],
                "code": "MC-1"
            },
            {
                "category": "High CVD risk",
                "definition": "High CVD risk",
                "conditions": [{
                    "cvd": ["CVD-HIGH-RISK"]
                }],
                "code": "MC-2"
            },
            {
                "category": "Very high or existing CVD",
                "definition": "high/very high risk",
                "conditions": [{
                    "cvd": ["CVD-VERY-HIGH-RISK", "CVD-EXISTING"]
                }],
                "code": "MC-3"
            }
        ],
        "blood_pressure_control": [{
            "category": "high",
            "definition": "high/very high risk",
            "conditions": [{
                "cvd": ["CVD-6", "CVD-1", "CVD-8", "CVD-10"],
                "diabetes": ["DM-EXISTING-GOOD-CONTROL", "DM-EXISTING-OVER-CONTROL", "DM-EXISTING-POOR-CONTROL", "DM-EXISTING-GOOD-CONTROL", "DM-NEW-DIAGNOSIS"],
                "blood_pressure": ["BP-EMERGENCY", "BP-HTN-REVIEW", "BP-HTN-DM", "BP-HTN", "BP-ELEVATED"]
            }],
            "code": "BPC-1"
        }],
        "blood_sugar_control": [{
                "category": "Needs better blood sugar control",
                "definition": "Existing or new diabetes +/- Poor Control",
                "conditions": [{
                    "diabetes": ["DM-EXISTING-OVER-CONTROL", "DM-EXISTING-POOR-CONTROL", "DM-NEW-DIAGNOSIS"]
                }],
                "code": "BSC-1"
            },
            {
                "category": "Lifestyle modification for prevention",
                "definition": "Pre-diabetes",
                "conditions": [{
                    "diabetes": ["DM-PRE-DIABETES"]
                }],
                "code": "BSC-2"
            }
        ],
        "cholesterol_control": []
    }
}
